[{"id":"1778937945022","name":"Banane","checked":true,"category":"produce"},{"id":"1778937883819","name":"Karfiol","checked":false,"category":"vegetables"},{"id":"1778937182541","name":"Otovent balon","checked":true,"category":"pharmacy"},{"id":"1778885647810","name":"Bijelo pilece","checked":false,"category":"meat"},{"id":"1778885638161","name":"Kore za strudlu","checked":true,"category":"pantry"},{"id":"1778885631671","name":"Sir meki kravlji","checked":true,"category":"dairy"},{"id":"1778885598469","name":"Acidofil","checked":true,"category":"dairy"},{"id":"1778885588933","name":"B-active","checked":false,"category":"dairy"},{"id":"1778885576830","name":"Kefir","checked":true,"category":"dairy"},{"id":"1778885567570","name":"Jogurt","checked":false,"category":"dairy"},{"id":"1778885563135","name":"Slatko vrhnje","checked":false,"category":"dairy"},{"id":"1778885550258","name":"Slag","checked":false,"category":"dairy"},{"id":"1778885546326","name":"Vrhnje za kuhanje","checked":false,"category":"dairy"},{"id":"1778885508545","name":"Rizini rezanci","checked":false,"category":"pantry"},{"id":"1778885494473","name":"Njoki","checked":false,"category":"frozen"},{"id":"1778885489885","name":"Fusili","checked":false,"category":"pantry"},{"id":"1778885485514","name":"Spageti","checked":false,"category":"pantry"},{"id":"1778885466506","name":"Sunka za tost","checked":true,"category":"meat"},{"id":"1778885457281","name":"Mascarpone","checked":false,"category":"dairy"},{"id":"1778885441055","name":"Prezle","checked":false,"category":"pantry"},{"id":"1778885389726","name":"Dimljeni losos - divlji","checked":false,"category":"frozen"},{"id":"1778885342549","name":"Celer stabljike","checked":false,"category":"vegetables"},{"id":"1778885298322","name":"Brokula","checked":false,"category":"vegetables"},{"id":"1778885286945","name":"Kupus","checked":false,"category":"vegetables"},{"id":"1778885280407","name":"Kelj","checked":false,"category":"vegetables"},{"id":"1778885277403","name":"Poriluk","checked":false,"category":"vegetables"},{"id":"1778885271446","name":"Grasak","checked":false,"category":"vegetables"},{"id":"1778885267012","name":"Rotkvica","checked":false,"category":"vegetables"},{"id":"1778885198157","name":"Ljutika","checked":false,"category":"vegetables"},{"id":"1778885185619","name":"Cesnjak","checked":false,"category":"vegetables"},{"id":"1778885180150","name":"Crveni luk","checked":false,"category":"vegetables"},{"id":"1778885174529","name":"Paprika zuta babura","checked":false,"category":"vegetables"},{"id":"1778885162995","name":"Paprika crvena rog","checked":false,"category":"vegetables"},{"id":"1778885144871","name":"Celer","checked":false,"category":"vegetables"},{"id":"1778885135864","name":"Persin","checked":false,"category":"vegetables"},{"id":"1778885130345","name":"Mrkva","checked":false,"category":"vegetables"},{"id":"1778885124822","name":"Blitva","checked":false,"category":"vegetables"},{"id":"1778885120672","name":"Salata","checked":false,"category":"vegetables"},{"id":"1778885114901","name":"Bob","checked":false,"category":"vegetables"},{"id":"1778885080249","name":"Riba","checked":false,"category":"fish"},{"id":"1778878164328","name":"Juneci misic za juhu","checked":true,"category":"meat"},{"id":"1778877972365","name":"Losos - pakiranje po 2","checked":true,"category":"frozen"},{"id":"1778877909888","name":"Riblji pritici - Fisheria","checked":true,"category":"frozen"},{"id":"1778876630764","name":"Tost","checked":false,"category":"bakery"},{"id":"1778872298254","name":"Pahuljice","checked":false,"category":"pantry"},{"id":"1778795912286","name":"Mlijeko","checked":false,"category":"dairy"},{"id":"1778795905285","name":"Kruh","checked":true,"category":"bakery"}]